Metadata-Version: 1.1
Name: pybitmap
Version: 0.0.3
Summary: 使用bitmap存储海量整型数据
Home-page: https://github.com/Alucardmini/basic_algrithms/blob/master/Bit_maps.py
Author: ghostcat_kun
Author-email: ghostcat_kun@163.com
License: UNKNOWN
Download-URL: https://github.com/Alucardmini/basic_algrithms/blob/master/Bit_maps.py
Keywords: bitmap,python,tool
Platform: UNKNOWN
